{
  "edinburgh": {
    "speakers": [
      {
        "name": "Tim Leslie",
        "talk": "Building a collaborative engineering culture"
      }
    ],
    "day": "8th",
    "month": "May"
  },
  "glasgow": {
    "speakers": [
      {
        "name": "Cancelled",
        "talk": "This months meetup has been cancelled"
      }
    ],
    "day": "22nd",
    "month": "Feb"
  },
  "stirling": {
    "speakers": [
     {
        "name": "Stacey Armour",
        "talk": "A talk about testing"
      }
    ],
    "day": "6th",
    "month": "May"
  },
  "aberdeen": {
    "speakers": [
      {
        "name": "Katie Lynn",
        "talk": "Scot.Gov's CivTech Programme"
      }
    ],
    "day": "15th",
    "month": "March"
  },
  "dundee": {
    "speakers": [
      {
        "name": "Todd Harding and Dr. Teodora Oniga from FindMyPast",
        "talk": "Deep Learning for Extracting Meaning from Free-Text Inputs"
      }
    ],
    "day": "29th",
    "month": "Nov"
  },
  "inverness": {
    "speakers": [
      {
        "name": "Open Mic Night",
        "talk": "Everyone is encourage to speak a little about their favourite dev tool."
      }
    ],
    "day": "23rd",
    "month": "Mar"
  }
}
